{"celestial":null,"dimensions":[794,477],"edit_signatures":[],"exif":{"camera":null,"datetime":null,"gps":null,"lens":null,"orientation":null,"resolution_dpi":null,"software":null,"tag_count":0},"jpeg_comment":null,"jpeg_markers":["APP0(JFIF)","APP14(Adobe)"],"marker_fingerprint":"Adobe+JFIF","notes":["no EXIF metadata \u2014 possibly stripped or never recorded","no GPS \u2014 location cannot be verified from metadata"],"phash":"c05d3f137e292f24","sha256":"30bb73bcdf7ba584cdbaabd4dc4375d77c49f4f73fce4bf4c516592795650f7c","size_bytes":41591}