{"celestial":null,"dimensions":[955,1241],"edit_signatures":[],"exif":{"camera":null,"datetime":null,"gps":null,"lens":null,"orientation":null,"resolution_dpi":null,"software":null,"tag_count":0},"jpeg_comment":null,"jpeg_markers":["APP0(JFIF)","APP14(Adobe)"],"marker_fingerprint":"Adobe+JFIF","notes":["no EXIF metadata \u2014 possibly stripped or never recorded","no GPS \u2014 location cannot be verified from metadata"],"phash":"d1b569ba6a542a0f","sha256":"2fb16e73628c771b7ba27472cb63b23a473413519a9e037ac43ee1ecc9e4183e","size_bytes":226302}