{"celestial":null,"dimensions":[860,1318],"edit_signatures":[],"exif":{"camera":null,"datetime":null,"gps":null,"lens":null,"orientation":null,"resolution_dpi":null,"software":null,"tag_count":0},"jpeg_comment":null,"jpeg_markers":["APP0(JFIF)","APP14(Adobe)"],"marker_fingerprint":"Adobe+JFIF","notes":["no EXIF metadata \u2014 possibly stripped or never recorded","no GPS \u2014 location cannot be verified from metadata"],"phash":"d5922ae057f14b39","sha256":"855da22a8b6a803050db049415519919c929766244ca97cc828c3664af1789de","size_bytes":166616}