{"celestial":null,"dimensions":[1584,1224],"edit_signatures":[],"exif":{"camera":null,"datetime":null,"gps":null,"lens":null,"orientation":null,"resolution_dpi":null,"software":null,"tag_count":0},"jpeg_comment":null,"jpeg_markers":["APP14(Adobe)"],"marker_fingerprint":"Adobe","notes":["no EXIF metadata \u2014 possibly stripped or never recorded","no GPS \u2014 location cannot be verified from metadata"],"phash":"eec49150c53aed6c","sha256":"dd003bd295e89a5cb0adeefc01cd595464e1b661d3fabeb104280489a6016fc8","size_bytes":183388}