{"id": "FBI_September_2023_Sighting_-_Serial_4", "title": "FBI September 2023 Sighting - Serial 4", "agency": "FBI", "type": "PDF", "release_date": "5/8/26", "incident_date": "9/1/23", "incident_location": "United States", "redaction": "TRUE", "blurb": "This is an FBI 302 interview conducted with a US citizen regarding their first-hand account of a UAP encounter at a US test site. USPER described an object \"metallic/gray in color.\"", "source_url": "https://www.war.gov/medialink/ufo/release_1/serial-3_redacted.pdf", "primary_local": ["raw/docs/serial-3_redacted.pdf"], "thumbnail_local": ["raw/images/serial-3_redacted.jpg"], "video_local": "", "dvids_video_id": "", "text": "-1 of 2-\n\nFEDERAL BUREAU OF INVESTIGATION\n\nFD-302 (Rev. 5-8-10)\n\nDate ofenty __LOMMJ/2023\n\nMM oo september 202), a a a 2:\nI HN, s«2@\"0._- FBI Special Agent J) PJ interviewed |\n(H--MNS ©@*f fiice ana | Ff Ff cell), in Building Jj\na ee ee ee ee ee ee\nec eee =: eee\n\nsupervisor sat in on the interview. After being advised of the identity of\n\nthe interviewing agents and the nature of the interview, [I] I\nprovided the following information:\n\ncee es\n\n(i Hs ©»:-:« PS September 2023, HE, 2s with QB contractors\n\nworking on a special project with J She had restricted the air space\nin || || for the upcoming tests. At 7:02 am, the contractors received\n\nthe bases’ standard fe Hs «© icf, got into three\n\nvehicles, and began driving to the site they were going to use for testing.\n\n(WBS 20 eho first venice with i\nMEE GE MS 22s Seco poscenscr. I A\ncontractors [ i = | were in the second and\n\nthird vehicles.\n\nio Between 7:15 and 7:30 am, ; drove down | | | toa\n\ngate that restricted access to part of the J FY attempted to open\nthe gate remotely using a fob. The gate opened just a little and then closed\non three separate tries. On the fourth attempt the gate opened completely\nand stayed open. There were no prior operational problems with that\nparticular gate and there were no operating issues with the gate after\n\nSeptember\n\n(il 4: HN) 2s criving through the gate she looked up and saw a\n\nee ee ee\nee eee\nEE\nInvestigationon 09 /MMJ/2023 at | Ff FF | United States (In Person)\nFic# i Date drafted 10 //2023\nty i\n\nThis document contains neither recommendations nor conclusions of the FBI. It is the property of the FBI and is loaned to your agency: it and its contents are not\nto be distributed outside your agency.\n\n\fFD-302a (Rev. 5-8-10)\n\nSeptember JJ 2023 IN BN var\nContinuation of FD-302 of On O9/MH/2023 page 2 of 2\n\ncigar shaped object with an extremely bright light southwest of them\napproximately 500 to 3000 feet above the nearest tree line (agent note: the\ntree line was approximately one mile south west of JJ position). The\nobject was already there when she looked up. The object was almost hovering,\nslowly moving from east to west. The light was an intense diamond white\nlight with what appeared to be a ring around the light and was located on\nthe eastern end of the object. The light was pointing south east and looking\nat it (the light) was like looking into the sun. The object was “metallic\nbronze in color” and was the length of two or three Blackhawk helicopters\nlined up nose to tail. The width of the object was approximately the width\nof one and a half Blackhawks but was hard to determine due the light on the\nobject’s eastern end which may have been obscuring part of the body. The\nobject was completely silent.\n\n(i ll HN) 2s initially annoyed when she saw the object because she\nhad restricted the ranges for the tests they were going to conduct that\nmorning but then she realized the object was not an aircraft or drone.\nWN,« sched her vehicle forward while she and [MJ watched the\nobject. They watched the object for five to ten seconds and then the object\njust disappeared. The sky was clear with no clouds and the object did leave\nany contrails. [J] 200 QJ searched the sky but did not see the\nobject again. [RBBB did not notice any interference with her vehicle’s\nengine while the object was visible. She only observed the one object and\nfelt it left when it saw them.\n\n(i ENS, @zxove to the test site where JJ IMJ who was a passenger\n\nin the second vehicle said he saw the object too.\n\n(i HN) 01 not have reported the object if she had seen it by\nherself. Several of her co-workers subsequently made fun of her due to her\n\nreport.\n\n(HEM sSNo photos or video of the object were taken by QJ or the\ncontractors. [MJ bad seen most of the aircraft and drones used by the\n\nUS military during her fifteen years working at J] EE] BJ end haa\nnever seen anything like the object she observed.\n", "similar_text": [{"id": "FBI_September_2023_Sighting_-_Serial_3", "title": "FBI September 2023 Sighting - Serial 3", "type": "PDF", "score": 0.519}, {"id": "FBI_September_2023_Sighting_-_Serial_5", "title": "FBI September 2023 Sighting - Serial 5", "type": "PDF", "score": 0.422}, {"id": "FBI_September_2023_Sighting_-_Composite_Sketch", "title": "FBI September 2023 Sighting - Composite Sketch", "type": "PDF", "score": 0.162}, {"id": "65_HS1-834228961_62-HQ-83894_Serial_438", "title": "65_HS1-834228961_62-HQ-83894_Serial_438", "type": "PDF", "score": 0.109}, {"id": "38_143685_box_Incident_Summaries_173-233", "title": "38_143685_box_Incident_Summaries_173-233", "type": "PDF", "score": 0.106}, {"id": "65_HS1-834228961_62-HQ-83894_Section_10", "title": "65_HS1-834228961_62-HQ-83894_Section_10", "type": "PDF", "score": 0.104}], "similar_image": [], "extracted_images": [], "craft_shape": "cigar", "incident_id": "", "tranche_id": "release-1-2026-05-08", "last_verified": "2026-05-09"}