{
  "results": {
    "id": "video:1006089",
    "type": "video",
    "title": "DOW-UAP-PR39, Unresolved UAP Report, Middle East, 2020",
    "description": "The United States Central Command submitted a report of an unidentified anomalous phenomenon to the All-domain Anomaly Resolution Office (AARO) consisting of five seconds of video footage from an infrared sensor aboard a U.S. military platform in 2020. The reporter did not provide any oral or written description of the observation.\r\n\r\nVideo Description:\r\n00:03-00:05: A faint area of contrast enters the sensor field-of-view from the bottom half of the right edge of the screen, proceeds from right to left across the corner of the frame, and exits the scene from near the center of the bottom edge of the screen.\r\n\r\nThis video description is provided for informational purposes only. Readers should not interpret any part of this description as reflecting an analytical judgment, investigative conclusion, or factual determination regarding the described event\u2019s validity, nature, or significance.",
    "keywords": "UAPVIDEOS",
    "date_published": "2026-05-08T07:47:01-04:00",
    "date": "2020-01-01T00:00:00-05:00",
    "category": "B-Roll",
    "unit_id": "8597",
    "unit_name": "All Domain Anomaly Resolution Office",
    "branch": "Civilian",
    "timestamp": "2026-05-08T07:58:49-04:00",
    "image": "https://d1ldvf68ux039x.cloudfront.net/thumbs/frames/video/2605/1006089/DOD_111689057.0000001/2000w_q95.jpg",
    "url": "https://www.dvidshub.net/video/1006089/dow-uap-pr39-unresolved-uap-report-middle-east-2020",
    "credit": "Courtesy",
    "location": {
      "city": "",
      "state": "",
      "country": "Undisclosed Location",
      "country_abbreviation": "UL"
    },
    "time_start": 0,
    "virin": "200102-D-D0360-2155",
    "duration": 5,
    "aspect_ratio": "16:9",
    "files": [
      {
        "src": "https://d34w7g4gy10iej.cloudfront.net/video/2605/DOD_111689057/DOD_111689057.mp4",
        "type": "video/mp4",
        "height": 1080,
        "width": 1920,
        "size": 1703321,
        "bitrate": 0
      },
      {
        "src": "https://d34w7g4gy10iej.cloudfront.net/video/2605/DOD_111689057/DOD_111689057-1920x1080-9000k.mp4",
        "type": "video/mp4",
        "height": 1080,
        "width": 1920,
        "size": 1749926,
        "bitrate": 0
      },
      {
        "src": "https://d34w7g4gy10iej.cloudfront.net/video/2605/DOD_111689057/DOD_111689057-1920x1080-6000k.mp4",
        "type": "video/mp4",
        "height": 1080,
        "width": 1920,
        "size": 1141129,
        "bitrate": 0
      },
      {
        "src": "https://d34w7g4gy10iej.cloudfront.net/video/2605/DOD_111689057/DOD_111689057-1280x720-3000k.mp4",
        "type": "video/mp4",
        "height": 720,
        "width": 1280,
        "size": 608505,
        "bitrate": 0
      },
      {
        "src": "https://d34w7g4gy10iej.cloudfront.net/video/2605/DOD_111689057/DOD_111689057-1024x576-2000k.mp4",
        "type": "video/mp4",
        "height": 576,
        "width": 1024,
        "size": 427072,
        "bitrate": 0
      },
      {
        "src": "https://d34w7g4gy10iej.cloudfront.net/video/2605/DOD_111689057/DOD_111689057-512x288-1000k.mp4",
        "type": "video/mp4",
        "height": 288,
        "width": 512,
        "size": 222346,
        "bitrate": 0
      },
      {
        "src": "https://d34w7g4gy10iej.cloudfront.net/video/2605/DOD_111689057/DOD_111689057-256x144-1000k.mp4",
        "type": "video/mp4",
        "height": 144,
        "width": 256,
        "size": 144846,
        "bitrate": 0
      }
    ],
    "hls_url": "https://api.dvidshub.net/hls/video/1006089.m3u8?api_key=key-68bb60d16b35e",
    "thumbnail": {
      "url": "https://d1ldvf68ux039x.cloudfront.net/thumbs/frames/video/2605/1006089/DOD_111689057.0000001/720w_q95.jpg",
      "width": 720,
      "height": 0
    }
  }
}